keplar_panel_integration_api/__init__.py
keplar_panel_integration_api/api_client.py
keplar_panel_integration_api/api_response.py
keplar_panel_integration_api/configuration.py
keplar_panel_integration_api/exceptions.py
keplar_panel_integration_api/py.typed
keplar_panel_integration_api/rest.py
keplar_panel_integration_api/api/__init__.py
keplar_panel_integration_api/api/default_api.py
keplar_panel_integration_api/models/__init__.py
keplar_panel_integration_api/models/api_call_messages_search_post200_response_inner.py
keplar_panel_integration_api/models/api_demos_create_demo_invite_post_request.py
keplar_panel_integration_api/models/api_files_file_id_signed_url_post200_response.py
keplar_panel_integration_api/models/api_files_file_id_signed_url_post_request.py
keplar_panel_integration_api/models/api_files_file_id_signed_url_post_request_action.py
keplar_panel_integration_api/models/api_invite_code_code_get200_response.py
keplar_panel_integration_api/models/api_invite_code_code_responses_response_id_put404_response.py
keplar_panel_integration_api/models/api_invite_code_code_responses_response_id_start_phone_call_post_request.py
keplar_panel_integration_api/models/api_invite_code_code_responses_response_id_update_call_put_request.py
keplar_panel_integration_api/models/api_invite_code_code_responses_response_id_update_call_put_request_call.py
keplar_panel_integration_api/models/api_invite_code_code_start_get302_response.py
keplar_panel_integration_api/models/api_invite_code_code_start_get302_response_project_config.py
keplar_panel_integration_api/models/api_invites_id_participant_invites_participant_id_put_request.py
keplar_panel_integration_api/models/api_invites_id_participant_invites_post_request.py
keplar_panel_integration_api/models/api_invites_id_participant_invites_post_request_participant.py
keplar_panel_integration_api/models/api_invites_id_put_request.py
keplar_panel_integration_api/models/api_invites_id_responses_get200_response.py
keplar_panel_integration_api-0.0.3.dist-info/METADATA
keplar_panel_integration_api-0.0.3.dist-info/WHEEL
keplar_panel_integration_api-0.0.3.dist-info/top_level.txt
keplar_panel_integration_api-0.0.3.dist-info/RECORD
